Metadata-Version: 2.1
Name: i6_models
Version: 1.20260120.115321
Summary: A collection of PyTorch NN models and parts.
Home-page: https://github.com/rwth-i6/i6_models/
Author: Christoph Lüscher, Nick Rossenbach, Benedikt Hilmes, Jingjing Xu, Mohammad Zeineldeen, Albert Zeyer, Peter Vieting, Simon Berger, Eugen Beck, Ping Zheng, Wilfried Michel
Author-email: luescher@cs.rwth-aachen.de, rossenbach@cs.rwth-aachen.de, hilmes@cs.rwth-aachen.de, jxu@cs.rwth-aachen.de, zeineldeen@cs.rwth-aachen.de, zeyer@cs.rwth-aachen.de, vieting@cs.rwth-aachen.de, sberger@cs.rwth-aachen.de, ebeck@apptek.com, p.zheng@apptek.com, wmichel@apptek.com
License: Mozilla Public License 2.0
Classifier: Programming Language :: Python :: 3
Classifier: License :: OSI Approved :: Mozilla Public License 2.0 (MPL 2.0)
Classifier: Operating System :: OS Independent
License-File: LICENSE
